{
    "ImagePlane":{
        "width":"INTEGER VALUE",
        "height": "INTEGER VALUE"
    },
    "Camera":{
        "position": {
            "x":"DOUBLE VALUE",
            "y":"DOUBLE VALUE",
            "z":"DOUBLE VALUE"
        },
        "pointOfView": {
            "x":"DOUBLE VALUE",
            "y":"DOUBLE VALUE",
            "z":"DOUBLE VALUE"
        },
		"cameraRightAngle": {
            "x":"DOUBLE VALUE",
            "y":"DOUBLE VALUE",
            "z":"DOUBLE VALUE"
        }
    },
    "Scene":{
      "Object3D":[
         {
            "Sphere":{
               "center":{
                  "x":"DOUBLE VALUE",
                  "y":"DOUBLE VALUE",
                  "z":"DOUBLE VALUE"
               },
               "radius":"DOUBLE VALUE",
               "color":{
                  "r":"INTEGER VALUE",
                  "g":"INTEGER VALUE",
                  "b":"INTEGER VALUE"
               },
               "specular":"DOUBLE VALUE", // 0 < specular < 1000
               "reflection":"DOUBLE VALUE", // 0.0 < reflection < 1.0
               "transparency":"DOUBLE VALUE", // 0.0 < transparency < 1.0
               "refractiveIndex":"DOUBLE VALUE" // 1.0 < transparency < 3.0
            }
         },
         {
            "Cube":{
               "center":{
                  "x":"DOUBLE VALUE",
                  "y":"DOUBLE VALUE",
                  "z":"DOUBLE VALUE"
               },
               "sideLength":"DOUBLE VALUE",
               "color":{
                  "r":"INTEGER VALUE",
                  "g":"INTEGER VALUE",
                  "b":"INTEGER VALUE"
               },
               "specular":"DOUBLE VALUE",
               "reflection":"DOUBLE VALUE",
               "transparency":"DOUBLE VALUE",
               "refractiveIndex":"DOUBLE VALUE"
            }
         }, 
         {
            "Cylinder":{
                "center":{
                    "x":"DOUBLE VALUE",
                    "y":"DOUBLE VALUE",
                    "z":"DOUBLE VALUE"
                 },
                 "radius":"DOUBLE VALUE",
                 "height":"DOUBLE VALUE",
                 "color":{
                    "r":"INTEGER VALUE",
                    "g":"INTEGER VALUE",
                    "b":"INTEGER VALUE"
                 },
                 "specular":"DOUBLE VALUE",
                 "reflection":"DOUBLE VALUE",
                 "transparency":"DOUBLE VALUE",
                 "refractiveIndex":"DOUBLE VALUE"
            }
        },
        {
            "Cone":{
                "center":{
                    "x":"DOUBLE VALUE",
                    "y":"DOUBLE VALUE",
                    "z":"DOUBLE VALUE"
                 },
                 "radius":"DOUBLE VALUE",
                 "height":"DOUBLE VALUE",
                 "color":{
                    "r":"INTEGER VALUE",
                    "g":"INTEGER VALUE",
                    "b":"INTEGER VALUE"
                 },
                 "specular":"DOUBLE VALUE",
                 "reflection":"DOUBLE VALUE",
                 "transparency":"DOUBLE VALUE",
                 "refractiveIndex":"DOUBLE VALUE"
            }
        }
      ],
      "Light":[
         {
            "center":{
               "x":"DOUBLE VALUE",
               "y":"DOUBLE VALUE",
               "z":"DOUBLE VALUE"
            },
            "brightness":"DOUBLE VALUE"
         }
      ],
      "AmbientLight":{
          "active":"BOOLEAN VALUE",
          "brightness":"DOUBLE VALUE"
      },
      "Floor":{
          "active":"BOOLEAN VALUE"
      },
	  "Room":{
          "active":"BOOLEAN VALUE"
      }
   }
}
